LICENSE
README.md
setup.py
CVE_2018_11784.egg-info/PKG-INFO
CVE_2018_11784.egg-info/SOURCES.txt
CVE_2018_11784.egg-info/dependency_links.txt
CVE_2018_11784.egg-info/entry_points.txt
CVE_2018_11784.egg-info/requires.txt
CVE_2018_11784.egg-info/top_level.txt
cve201811784/__init__.py
cve201811784/main.py
cve201811784/includes/__init__.py
cve201811784/includes/bot.py
cve201811784/includes/filereader.py
cve201811784/includes/scan.py
cve201811784/includes/writefile.py
cve201811784/utils/__init__.py
cve201811784/utils/configure.py
cve201811784/utils/const.py
cve201811784/utils/helpers.py
cve201811784/utils/status.py